napalm_core/__init__.py
napalm_core/detectors/__init__.py
napalm_core/detectors/chainlink_price_feed.py
napalm_core/detectors/environment/block_timestamp.yml
napalm_core/detectors/environment/block_timestamp_swap.yaml
napalm_core/detectors/loop_array_dos.py
napalm_core/detectors/token_interface/__init__.py
napalm_core/detectors/token_interface/erc20_approve_call.py
napalm_core/detectors/token_interface/erc721_stuck_mint.py
napalm_core/detectors/token_interface/erc721_stuck_transfer_from.py
napalm_core/detectors/token_interface/unsafe_erc20.yaml
napalm_core/detectors/unchecked_return_value/__init__.py
napalm_core/detectors/unchecked_return_value/create2_unchecked_return.py
napalm_core/detectors/unchecked_return_value/erc20_unchecked_approve.py
napalm_core/detectors/unchecked_return_value/unrequired_equation.py
napalm_core/detectors/util/__init__.py
napalm_core/detectors/util/post_dominators.py
napalm_core/detectors/util/taint.py
napalm_core/detectors/util/unused_return_values.py
napalm_core/indicators/__init__.py
napalm_core/indicators/blocknumber.yaml
napalm_core/indicators/privilege.yml
napalm_core/indicators/push0_solidity_version.py
napalm_core/indicators/solmate.yaml
napalm_core/indicators/unchecked.yml
napalm_core/napalm.py
napalm_core/optimisations/__init__.py
napalm_core/optimisations/simple-gas-optimisations.yml
napalm_core-0.1.2.dist-info/LICENSE
napalm_core-0.1.2.dist-info/METADATA
napalm_core-0.1.2.dist-info/WHEEL
napalm_core-0.1.2.dist-info/entry_points.txt
napalm_core-0.1.2.dist-info/RECORD
