Metadata-Version: 2.1
Name: napalm-core
Version: 0.1.2
Summary: Your project to manage napalm detection modules
License: AGPL-3.0
Requires-Python: >=3.10,<4.0
Classifier: License :: OSI Approved :: GNU Affero General Public License v3
Classifier: Programming Language :: Python :: 3
Classifier: Programming Language :: Python :: 3.10
Classifier: Programming Language :: Python :: 3.11
Requires-Dist: slither-analyzer (>=0.10,<0.11)
